[
    {
        "model": "takeaway.menu_item",
        "pk": 1,
        "fields": {
            "item_name": "Egg Curry",
            "selling_price": 300
        }
    },
    {
        "model": "takeaway.inventory",
        "pk": 1,
        "fields": {
            "ingredient_name": "Egg",
            "quantity": 67200,
            "min_quantity": 1000,
            "cost_price": 30
        }
    },
    {
        "model": "takeaway.inventory",
        "pk": 2,
        "fields": {
            "ingredient_name": "Salt",
            "quantity": 19720,
            "min_quantity": 1000,
            "cost_price": 20
        }
    },
    {
        "model": "takeaway.ingredient_list",
        "pk": 1,
        "fields": {
            "item": 1,
            "ingredient": 1,
            "use_quantity": 100
        }
    },
    {
        "model": "takeaway.ingredient_list",
        "pk": 2,
        "fields": {
            "item": 1,
            "ingredient": 2,
            "use_quantity": 10
        }
    }
]